README.md
setup.py
SLRanger/SL_detect.py
SLRanger/__init__.py
SLRanger/add_gene.py
SLRanger/calculate_acc_per_bam.py
SLRanger/calculate_pr.py
SLRanger/mimic_test.py
SLRanger/operon_predict.py
SLRanger/run_ex_function.py
SLRanger/visualization.py
SLRanger/yw_test.py
SLRanger.egg-info/PKG-INFO
SLRanger.egg-info/SOURCES.txt
SLRanger.egg-info/dependency_links.txt
SLRanger.egg-info/requires.txt
SLRanger.egg-info/top_level.txt