Metadata-Version: 2.1
Name: SLRanger
Version: 0.0.1.8
Summary: An integrated approach for spliced leader detection and operon prediction in eukaryotes using long RNA reads
Home-page: https://github.com/lrslab/SLRanger
Author: GUO Zhihao
Author-email: qhuozhihao@icloud.com
Classifier: Programming Language :: Python :: 3
Classifier: License :: OSI Approved :: MIT License
Classifier: Operating System :: OS Independent
Requires-Python: >=3.7.0,<=3.11.7
Requires-Dist: bio>=1.5.0
Requires-Dist: numpy<2.0.0,>=1.23.0
Requires-Dist: pandas>=2.1.0
Requires-Dist: plotnine>=0.12.4
Requires-Dist: tqdm>=4.0.0
Requires-Dist: pysam>=0.21.0
Requires-Dist: biopython>=1.80
Requires-Dist: pyssw==0.1.7
Requires-Dist: trackcluster==0.1.7
Requires-Dist: scikit-learn>=1.0.2
Requires-Dist: tabulate>=0.8.0
Requires-Dist: Markdown>=3.5
Requires-Dist: seaborn>0.12.0
